ghidrecomp/__init__.py
ghidrecomp/__main__.py
ghidrecomp/bsim.py
ghidrecomp/callgraph.py
ghidrecomp/decompile.py
ghidrecomp/parser.py
ghidrecomp/sast.py
ghidrecomp/utility.py
ghidrecomp-0.5.9.dist-info/licenses/LICENSE
ghidrecomp-0.5.9.dist-info/METADATA
ghidrecomp-0.5.9.dist-info/WHEEL
ghidrecomp-0.5.9.dist-info/entry_points.txt
ghidrecomp-0.5.9.dist-info/top_level.txt
ghidrecomp-0.5.9.dist-info/RECORD
