Metadata-Version: 2.4
Name: ghidrecomp
Version: 0.5.9
Summary: Python Command-Line Ghidra Decomplier
Home-page: https://github.com/clearbluejar/ghidrecomp
Author: clearbluejar
Author-email: clearbluejar@clearbluejar.com
License: GPL-3.0 license
Keywords: ghidra,decompiler,callgraph,bsim
Platform: any
Classifier: Development Status :: 3 - Alpha
Classifier: Intended Audience :: Developers
Classifier: License :: OSI Approved :: GNU General Public License v3 (GPLv3)
Classifier: Programming Language :: Python :: 3
Classifier: Programming Language :: Python :: 3.10
Classifier: Programming Language :: Python :: 3.11
Classifier: Programming Language :: Python :: 3.12
Requires-Python: >=3.10
License-File: LICENSE
Requires-Dist: pyghidra>=2.2.1
Provides-Extra: sast
Requires-Dist: semgrep; extra == "sast"
Provides-Extra: testing
Requires-Dist: pytest; extra == "testing"
Requires-Dist: pytest-datadir; extra == "testing"
Dynamic: license-file
